mplotlab/__init__.py
mplotlab/graphics/ConfigPanel.py
mplotlab/graphics/GraphicBook.py
mplotlab/graphics/GraphicCtlr.py
mplotlab/graphics/GraphicPanel.py
mplotlab/graphics/MainWin.py
mplotlab/graphics/Navigation.py
mplotlab/graphics/PyObjectProperty.py
mplotlab/graphics/ShellPanel.py
mplotlab/graphics/TreePanel.py
mplotlab/graphics/__init__.py
mplotlab/models/AbcModel.py
mplotlab/models/AbcType.py
mplotlab/models/Collection.py
mplotlab/models/Container.py
mplotlab/models/Projection.py
mplotlab/models/Slide.py
mplotlab/models/Source.py
mplotlab/models/Variable.py
mplotlab/models/__init__.py
mplotlab/mpl_builders/__init__.py
mplotlab/mpl_builders/mpl_animations.py
mplotlab/mpl_builders/mpl_figures.py
mplotlab/utils/ErrorMgr.py
mplotlab/utils/Logger.py
mplotlab/utils/ParamMgr.py
mplotlab/utils/__init__.py
mplotlab-0.2.dist-info/DESCRIPTION.rst
mplotlab-0.2.dist-info/METADATA
mplotlab-0.2.dist-info/RECORD
mplotlab-0.2.dist-info/WHEEL
mplotlab-0.2.dist-info/metadata.json
mplotlab-0.2.dist-info/top_level.txt
