Metadata-Version: 2.0
Name: mplotlab
Version: 0.2
Summary: Interactive Matplotlib Application using wxPython
Home-page: UNKNOWN
Author: Andre ASTYL
Author-email: andreastyl@gmail.com
License: MIT License
Download-URL: http://github.com/astyl/mplotlab/
Platform: Windows
Platform: Linux
Platform: Mac OS X
Classifier: Intended Audience :: Science/Research
Classifier: Operating System :: OS Independent
Classifier: Programming Language :: Python
Classifier: Topic :: Scientific/Engineering
Classifier: Topic :: Scientific/Engineering :: Visualization
Requires: wx
Requires: numpy
Requires: matplotlib
